segnivo_sdk/__init__.py
segnivo_sdk/api_client.py
segnivo_sdk/api_response.py
segnivo_sdk/configuration.py
segnivo_sdk/exceptions.py
segnivo_sdk/py.typed
segnivo_sdk/rest.py
segnivo_sdk/api/__init__.py
segnivo_sdk/api/email_address_verification_api.py
segnivo_sdk/api/email_campaigns_api.py
segnivo_sdk/api/mailing_lists_api.py
segnivo_sdk/api/relay_api.py
segnivo_sdk/api/relay_transactional_emails_api.py
segnivo_sdk/api/subscribers_contacts_api.py
segnivo_sdk/models/__init__.py
segnivo_sdk/models/add_contact_request.py
segnivo_sdk/models/campaign_create_request.py
segnivo_sdk/models/campaign_update_request.py
segnivo_sdk/models/contact_update_request.py
segnivo_sdk/models/contacts_uid_add_tag_post_request.py
segnivo_sdk/models/email_address_verification_request.py
segnivo_sdk/models/mailing_list_add_field_request.py
segnivo_sdk/models/mailing_list_request.py
segnivo_sdk/models/mailing_list_request_contact.py
segnivo_sdk/models/relay_email_request.py
segnivo_python_sdk-1.7.16.dist-info/METADATA
segnivo_python_sdk-1.7.16.dist-info/WHEEL
segnivo_python_sdk-1.7.16.dist-info/top_level.txt
segnivo_python_sdk-1.7.16.dist-info/RECORD
